LICENSE
README.md
setup.cfg
setup.py
test/test_rooms.py
websocket_rooms/__init__.py
websocket_rooms/room.py
websocket_rooms.egg-info/PKG-INFO
websocket_rooms.egg-info/SOURCES.txt
websocket_rooms.egg-info/dependency_links.txt
websocket_rooms.egg-info/requires.txt
websocket_rooms.egg-info/top_level.txt