Metadata-Version: 2.1
Name: websocket-rooms
Version: 0.1.1
Summary: Python library for simple websocket managment
Home-page: https://github.com/yoelbassin/Websocket-Rooms
Author: Yoel Bassin
Author-email: bassin.yoel@gmail.com
License: MIT
Platform: UNKNOWN
Classifier: Development Status :: 2 - Pre-Alpha
Classifier: Environment :: Web Environment
Classifier: Framework :: AnyIO
Classifier: Topic :: Internet :: WWW/HTTP
Classifier: Operating System :: OS Independent
Classifier: Intended Audience :: Developers
Classifier: License :: OSI Approved :: MIT License
Classifier: Programming Language :: Python
Provides-Extra: example
Provides-Extra: test
License-File: LICENSE
